nonos/__init__.py
nonos/_backports.py
nonos/_geometry.py
nonos/_types.py
nonos/default.mplstyle
nonos/loaders.py
nonos/py.typed
nonos/styling.py
nonos/_readers/__init__.py
nonos/_readers/binary.py
nonos/_readers/ini.py
nonos/_readers/planet.py
nonos/api/__init__.py
nonos/api/_angle_parsing.py
nonos/api/analysis.py
nonos/api/satellite.py
nonos/api/tools.py
nonos-0.19.0.dist-info/licenses/LICENSE
nonos-0.19.0.dist-info/WHEEL
nonos-0.19.0.dist-info/METADATA
nonos-0.19.0.dist-info/RECORD
