Metadata-Version: 2.4
Name: nonos
Version: 0.19.0
Summary: A lightweight plotting library for protoplanetary disks simulations
Author: G. Wafflard-Fernandez, C.M.T. Robert
Requires-Python: >=3.10
License-Expression: GPL-3.0-only
Classifier: Development Status :: 4 - Beta
Classifier: Framework :: Matplotlib
Classifier: Intended Audience :: Science/Research
Classifier: Programming Language :: Python :: 3
Classifier: Programming Language :: Python :: 3.10
Classifier: Programming Language :: Python :: 3.11
Classifier: Programming Language :: Python :: 3.12
Classifier: Programming Language :: Python :: 3.13
Classifier: Programming Language :: Python :: 3.14
Classifier: Programming Language :: Python :: Implementation :: CPython
Classifier: Topic :: Scientific/Engineering :: Visualization
Classifier: Typing :: Typed
License-File: LICENSE
Requires-Dist: inifix>=5.1.0
Requires-Dist: matplotlib>=3.5.0
Requires-Dist: numpy>=1.21.2
Requires-Dist: typing_extensions >= 4.4.0 ; python_version < '3.12'
Requires-Dist: nonos[cli] ; extra == "all"
Requires-Dist: cblind>=2.3.0 ; extra == "all"
Requires-Dist: cmocean>=3.0.3 ; extra == "all"
Requires-Dist: cmyt>=2.0.0 ; extra == "all"
Requires-Dist: lick>=0.5.1 ; extra == "all"
Requires-Dist: scipy>=1.7.2 ; extra == "all"
Requires-Dist: nonos-cli>=0.1.0 ; extra == "cli"
Project-URL: Homepage, https://github.com/la-niche/nonos
Provides-Extra: all
Provides-Extra: cli
